MANIFEST.in
README.rst
setup.py
twilio_thinQLCR_python/__init__.py
twilio_thinQLCR_python.egg-info/PKG-INFO
twilio_thinQLCR_python.egg-info/SOURCES.txt
twilio_thinQLCR_python.egg-info/dependency_links.txt
twilio_thinQLCR_python.egg-info/not-zip-safe
twilio_thinQLCR_python.egg-info/requires.txt
twilio_thinQLCR_python.egg-info/top_level.txt