Metadata-Version: 1.0
Name: twilio-thinQLCR-python
Version: 0.1
Summary: Twilio Wrapper Library For thinQ LCR integration.
Home-page: https://github.com/harouf/twilio-thinQLCR-python
Author: Fujio Harou
Author-email: harouf@outlook.com
License: MIT
Keywords: twilio thinq wrapper
Platform: UNKNOWN
